mpesapy/__init__.py
mpesapy-1.0.1.dist-info/METADATA
mpesapy-1.0.1.dist-info/RECORD
mpesapy-1.0.1.dist-info/WHEEL
mpesapy-1.0.1.dist-info/top_level.txt
