Metadata-Version: 2.1
Name: mpesapy
Version: 1.0.1
Summary: Wrapper for M-pesa daraja api
Home-page: https://github.com/dennismwagiru/mpesapy
Author: Dennis Mwagiru
Author-email: dennismwagiru@gmail.com
License: MIT
Platform: UNKNOWN
Classifier: License :: OSI Approved :: MIT License
Classifier: Operating System :: OS Independent
Requires-Dist: requests
